MANIFEST.in
setup.cfg
setup.py
./.gitignore
./.travis.yml
./CHANGELOG.md
./Dockerfile
./LICENSE
./MANIFEST.in
./README.md
./ctfd.ini
./development.txt
./docker-compose.yml
./docker-entrypoint.sh
./export.py
./import.py
./manage.py
./populate.py
./prepare.sh
./requirements.txt
./serve.py
./setup.cfg
./setup.py
./wsgi.py
./CTFd/__init__.py
./CTFd/auth.py
./CTFd/challenges.py
./CTFd/config.py
./CTFd/models.py
./CTFd/scoreboard.py
./CTFd/utils.py
./CTFd/views.py
./CTFd/admin/__init__.py
./CTFd/admin/challenges.py
./CTFd/admin/containers.py
./CTFd/admin/keys.py
./CTFd/admin/pages.py
./CTFd/admin/scoreboard.py
./CTFd/admin/statistics.py
./CTFd/admin/teams.py
./CTFd/logs/.gitkeep
./CTFd/plugins/__init__.py
./CTFd/plugins/challenges/__init__.py
./CTFd/plugins/keys/__init__.py
./CTFd/themes/admin/static/css/style.css
./CTFd/themes/admin/static/css/vendor/bootstrap.min.css
./CTFd/themes/admin/static/css/vendor/codemirror.min.css
./CTFd/themes/admin/static/css/vendor/lato.css
./CTFd/themes/admin/static/css/vendor/raleway.css
./CTFd/themes/admin/static/css/vendor/font-awesome/HELP-US-OUT.txt
./CTFd/themes/admin/static/css/vendor/font-awesome/css/font-awesome.css
./CTFd/themes/admin/static/css/vendor/font-awesome/css/font-awesome.min.css
./CTFd/themes/admin/static/css/vendor/font-awesome/fonts/FontAwesome.otf
./CTFd/themes/admin/static/css/vendor/font-awesome/fonts/fontawesome-webfont.eot
./CTFd/themes/admin/static/css/vendor/font-awesome/fonts/fontawesome-webfont.svg
./CTFd/themes/admin/static/css/vendor/font-awesome/fonts/fontawesome-webfont.ttf
./CTFd/themes/admin/static/css/vendor/font-awesome/fonts/fontawesome-webfont.woff
./CTFd/themes/admin/static/css/vendor/font-awesome/fonts/fontawesome-webfont.woff2
./CTFd/themes/admin/static/css/vendor/font-awesome/less/animated.less
./CTFd/themes/admin/static/css/vendor/font-awesome/less/bordered-pulled.less
./CTFd/themes/admin/static/css/vendor/font-awesome/less/core.less
./uctfd.egg-info/PKG-INFO
./uctfd.egg-info/SOURCES.txt
./uctfd.egg-info/dependency_links.txt
./uctfd.egg-info/top_level.txt
uctfd.egg-info/PKG-INFO
uctfd.egg-info/SOURCES.txt
uctfd.egg-info/dependency_links.txt
uctfd.egg-info/top_level.txt