Metadata-Version: 1.0
Name: uctfd
Version: 1.0.3.post1
Summary: Unofficial CTFd split for pypi.
Home-page: UNKNOWN
Author: UNKNOWN
Author-email: UNKNOWN
License: UNKNOWN
Platform: UNKNOWN
